Metadata-Version: 1.1
Name: copydog
Version: 0.1
Summary: Copies issues between Redmine and Trello on the fly
Home-page: http://copydog.readthedocs.org/
Author: coagulant
Author-email: baryshev@gmail.com
License: BSD
Platform: UNKNOWN
Classifier: Development Status :: 3 - Alpha
Classifier: Intended Audience :: Developers
